odoo/addons/l10n_fr_ecotaxe_product/README.rst
odoo/addons/l10n_fr_ecotaxe_product/__init__.py
odoo/addons/l10n_fr_ecotaxe_product/__manifest__.py
odoo/addons/l10n_fr_ecotaxe_product/i18n/l10n_fr_ecotaxe_product.pot
odoo/addons/l10n_fr_ecotaxe_product/models/__init__.py
odoo/addons/l10n_fr_ecotaxe_product/models/product_product.py
odoo/addons/l10n_fr_ecotaxe_product/readme/CONTRIBUTORS.rst
odoo/addons/l10n_fr_ecotaxe_product/readme/DESCRIPTION.rst
odoo/addons/l10n_fr_ecotaxe_product/readme/USAGE.rst
odoo/addons/l10n_fr_ecotaxe_product/static/description/icon.png
odoo/addons/l10n_fr_ecotaxe_product/static/description/index.html
odoo/addons/l10n_fr_ecotaxe_product/tests/__init__.py
odoo/addons/l10n_fr_ecotaxe_product/tests/common.py
odoo/addons/l10n_fr_ecotaxe_product/tests/test_invoice_ecotaxe.py
odoo/addons/l10n_fr_ecotaxe_product/tests/test_product_ecotaxe.py
odoo_addon_l10n_fr_ecotaxe_product-15.0.1.0.0.3.dist-info/METADATA
odoo_addon_l10n_fr_ecotaxe_product-15.0.1.0.0.3.dist-info/WHEEL
odoo_addon_l10n_fr_ecotaxe_product-15.0.1.0.0.3.dist-info/top_level.txt
odoo_addon_l10n_fr_ecotaxe_product-15.0.1.0.0.3.dist-info/RECORD
